pybug/__init__.py
pybug/colors.py
pybug/errors.py
pybug/initialisation.py
pybug/search.py
py_bugs-1.dist-info/LICENSE
py_bugs-1.dist-info/METADATA
py_bugs-1.dist-info/WHEEL
py_bugs-1.dist-info/top_level.txt
py_bugs-1.dist-info/RECORD
