Metadata-Version: 2.1
Name: py-bugs
Version: 1
Summary: The all-in-one Python debugging solution
Home-page: https://github.com/Alex-Jando/PyBug
Author: Alex-Jando
Author-email: alexjando2007@outlook.com
Project-URL: Bug Tracker, https://github.com/Alex-Jando/PyBug/issues
Classifier: Programming Language :: Python :: 3
Classifier: License :: OSI Approved :: MIT License
Classifier: Operating System :: OS Independent
Requires-Python: >=3.9
License-File: LICENSE
